{"ongoing_trials": {}, "hyperparameters": {"space": [{"class_name": "Int", "config": {"name": "gru_units", "default": null, "conditions": [], "min_value": 64, "max_value": 256, "step": 32, "sampling": "linear"}}, {"class_name": "Int", "config": {"name": "lstm_units", "default": null, "conditions": [], "min_value": 64, "max_value": 256, "step": 32, "sampling": "linear"}}, {"class_name": "Int", "config": {"name": "dense_units", "default": null, "conditions": [], "min_value": 16, "max_value": 64, "step": 16, "sampling": "linear"}}, {"class_name": "Float", "config": {"name": "dropout_rate", "default": 0.01, "conditions": [], "min_value": 0.01, "max_value": 0.5, "step": 0.01, "sampling": "linear"}}, {"class_name": "Float", "config": {"name": "learning_rate", "default": 1e-05, "conditions": [], "min_value": 1e-05, "max_value": 0.01, "step": null, "sampling": "log"}}, {"class_name": "Int", "config": {"name": "batch_size", "default": null, "conditions": [], "min_value": 4, "max_value": 128, "step": 2, "sampling": "log"}}], "values": {"gru_units": 64, "lstm_units": 64, "dense_units": 16, "dropout_rate": 0.01, "learning_rate": 1e-05, "batch_size": 4}}, "start_order": ["00", "01", "02", "03", "04", "05", "06", "07", "08", "09"], "end_order": ["00", "01", "02", "03", "04", "05", "06", "07", "08", "09"], "run_times": {"00": 1, "01": 1, "02": 1, "03": 1, "04": 1, "05": 1, "06": 1, "07": 1, "08": 1, "09": 1}, "retry_queue": [], "seed": 120, "seed_state": 179, "tried_so_far": ["452dab55a1118330ed7ccfc375ba9b79", "185717203b11791448b0c943d4561a63", "31792c0dff82ae316e59282938ff8880", "7709182cd2a1da6100638936a1125d17", "767de4a3317fa45c87cae7c0da284a96", "7e52c8de37fb8319a3eeb1d4127dbf7c", "4eda0c717df674d160ea66d94c2671d8", "bacc2d0f870108cec6245325c0b5a6cf", "59389ff44cb175ff5c2597ec05395222", "a580ffaeb0e4be69581509c6d01306e6"], "id_to_hash": {"00": "31792c0dff82ae316e59282938ff8880", "01": "bacc2d0f870108cec6245325c0b5a6cf", "02": "185717203b11791448b0c943d4561a63", "03": "452dab55a1118330ed7ccfc375ba9b79", "04": "4eda0c717df674d160ea66d94c2671d8", "05": "767de4a3317fa45c87cae7c0da284a96", "06": "7e52c8de37fb8319a3eeb1d4127dbf7c", "07": "a580ffaeb0e4be69581509c6d01306e6", "08": "59389ff44cb175ff5c2597ec05395222", "09": "7709182cd2a1da6100638936a1125d17"}, "display": {"search_start": "2024-11-18T13:58:37.403855", "trial_start": {"00": "2024-11-18T13:58:37.403855", "01": "2024-11-18T14:00:04.514511", "02": "2024-11-18T14:00:31.275759", "03": "2024-11-18T14:00:47.368434", "04": "2024-11-18T14:01:04.154752", "05": "2024-11-18T14:01:50.478930", "06": "2024-11-18T14:02:18.825227", "07": "2024-11-18T14:04:14.558706", "08": "2024-11-18T14:05:10.349834", "09": "2024-11-18T14:05:44.395985"}, "trial_number": {"00": 1, "01": 2, "02": 3, "03": 4, "04": 5, "05": 6, "06": 7, "07": 8, "08": 9, "09": 10}}}